ai/backend/integration/jupyter/__init__.py
ai/backend/integration/jupyter/__main__.py
ai/backend/integration/jupyter/install.py
ai/backend/integration/jupyter/kernel.py
sorna/integration/jupyter/__init__.py
sorna/integration/jupyter/__main__.py
sorna/integration/jupyter/install.py
sorna/integration/jupyter/kernel.py
backend.ai_integration_jupyter-0.3.2.dist-info/LICENSE
backend.ai_integration_jupyter-0.3.2.dist-info/METADATA
backend.ai_integration_jupyter-0.3.2.dist-info/WHEEL
backend.ai_integration_jupyter-0.3.2.dist-info/top_level.txt
backend.ai_integration_jupyter-0.3.2.dist-info/RECORD
