Metadata-Version: 2.1
Name: backend.ai-integration-jupyter
Version: 0.3.2
Summary: Backend.AI Integration for Jupyter
Home-page: https://github.com/lablup/backend.ai-integration-jupyter
Author: Lablup Inc.
Author-email: joongi@lablup.com
License: MIT
Project-URL: Source, https://github.com/lablup/backend.ai-integration-jupyter
Project-URL: Tracker, https://github.com/lablup/backend.ai-integration-jupyter/issues
Project-URL: Documentation, http://docs.backend.ai
Platform: UNKNOWN
Classifier: Development Status :: 4 - Beta
Classifier: License :: OSI Approved :: MIT License
Classifier: Intended Audience :: Developers
Classifier: Programming Language :: Python
Classifier: Programming Language :: Python :: 3
Classifier: Programming Language :: Python :: 3.5
Classifier: Programming Language :: Python :: 3.6
Classifier: Operating System :: POSIX
Classifier: Operating System :: MacOS :: MacOS X
Classifier: Environment :: No Input/Output (Daemon)
Classifier: Topic :: Scientific/Engineering
Classifier: Topic :: Software Development
Requires-Python: >=3.5
Requires-Dist: backend.ai-client (<1.5.0,>=1.4.0)
Requires-Dist: metakernel (~=0.20.14)
Provides-Extra: build
Requires-Dist: wheel (>=0.31.0); extra == 'build'
Requires-Dist: twine (>=0.11.0); extra == 'build'
Provides-Extra: dev
Requires-Dist: pytest; extra == 'dev'
Requires-Dist: flake8; extra == 'dev'
Provides-Extra: test
Requires-Dist: pytest; extra == 'test'
